yapcc/__init__.py
yapcc/cli.py
yapcc-0.0.1.dist-info/COPYING
yapcc-0.0.1.dist-info/METADATA
yapcc-0.0.1.dist-info/WHEEL
yapcc-0.0.1.dist-info/entry_points.txt
yapcc-0.0.1.dist-info/top_level.txt
yapcc-0.0.1.dist-info/RECORD
