Metadata-Version: 2.1
Name: yapcc
Version: 0.0.1
Summary: Yet Another Python C compiler
Author-email: Jon Webb <jon@jonwebb.dev>
Project-URL: Homepage, https://github.com/jon-codes/yapcc
Project-URL: Repository, https://github.com/jon-codes/yapcc.git
Project-URL: Issues, https://github.com/jon-codes/yapcc/issues
Classifier: Development Status :: 3 - Alpha
Classifier: Programming Language :: Python :: 3
Classifier: License :: OSI Approved :: GNU General Public License v3 (GPLv3)
Requires-Python: >=3.12
License-File: COPYING
